tstock/__init__.py
tstock/__main__.py
tstock/core.py
tstock/parse.py
tstock/settings.py
tstock-2.2.6.dist-info/LICENSE
tstock-2.2.6.dist-info/METADATA
tstock-2.2.6.dist-info/WHEEL
tstock-2.2.6.dist-info/entry_points.txt
tstock-2.2.6.dist-info/top_level.txt
tstock-2.2.6.dist-info/RECORD
