Metadata-Version: 2.1
Name: tstock
Version: 2.2.6
Summary: A command line tool for generating stock charts in the terminal.
Home-page: https://github.com/Gbox4/tstock
Author: Gabe Banks
Author-email: gabriel.t.banks@gmail.com
License: UNKNOWN
Keywords: tstock stock ticker finance crypto
Platform: UNKNOWN
Classifier: Programming Language :: Python :: 3.6
Classifier: License :: OSI Approved :: GNU General Public License v3 or later (GPLv3+)
Classifier: Operating System :: OS Independent
Requires-Python: >=3.6
License-File: LICENSE
Requires-Dist: requests
Requires-Dist: numpy
